pysonic/__init__.py
pysonic/client.py
python_sonic_client-0.0.8.dist-info/METADATA
python_sonic_client-0.0.8.dist-info/WHEEL
python_sonic_client-0.0.8.dist-info/top_level.txt
python_sonic_client-0.0.8.dist-info/RECORD
