Metadata-Version: 2.1
Name: python-sonic-client
Version: 0.0.8
Summary: Python client for Sonic Search DB
Home-page: https://github.com/cyprx/pysonic
Author: cyprx
Author-email: cyprx@outlook.com
License: MIT
Platform: UNKNOWN
Classifier: License :: OSI Approved :: MIT License
Classifier: Programming Language :: Python :: 3
Classifier: Programming Language :: Python :: 3.7
